{
  "exports": [
    {
      "export_id": "export_chat_20260702_132055_884497",
      "chat_id": "chat_20260702_132055_884497",
      "chat_title": "test for chat export",
      "exported_at": "2026-07-02T13:24:34.776419+00:00",
      "message_count": 4,
      "txt_path": "data\\exports\\export_chat_20260702_132055_884497\\test_for_chat_export.txt",
      "md_path": "data\\exports\\export_chat_20260702_132055_884497\\test_for_chat_export.md",
      "json_path": "data\\exports\\export_chat_20260702_132055_884497\\test_for_chat_export.json"
    },
    {
      "export_id": "export_chat_20260702_115326_037231",
      "chat_id": "chat_20260702_115326_037231",
      "chat_title": "mind mapmodule",
      "exported_at": "2026-07-02T13:32:31.416950+00:00",
      "message_count": 12,
      "txt_path": "data\\exports\\export_chat_20260702_115326_037231\\mind_mapmodule.txt",
      "md_path": "data\\exports\\export_chat_20260702_115326_037231\\mind_mapmodule.md",
      "json_path": "data\\exports\\export_chat_20260702_115326_037231\\mind_mapmodule.json"
    }
  ]
}